snnax/__init__.py
snnax/functional/__init__.py
snnax/functional/surrogate.py
snnax/snn/__init__.py
snnax/snn/architecture.py
snnax/snn/composed.py
snnax/snn/layers/__init__.py
snnax/snn/layers/flatten.py
snnax/snn/layers/iaf.py
snnax/snn/layers/li.py
snnax/snn/layers/lif.py
snnax/snn/layers/maxpool2d.py
snnax/snn/layers/srm.py
snnax/snn/layers/stateful.py
snnax/utils/__init__.py
snnax/utils/tree.py
snnax-0.0.1.dist-info/AUTHORS.rst
snnax-0.0.1.dist-info/LICENSE.txt
snnax-0.0.1.dist-info/METADATA
snnax-0.0.1.dist-info/WHEEL
snnax-0.0.1.dist-info/top_level.txt
snnax-0.0.1.dist-info/RECORD
